ckanext/__init__.py
ckanext/chatbot/__init__.py
ckanext/chatbot/cli.py
ckanext/chatbot/const.py
ckanext/chatbot/plugin.py
ckanext/chatbot/types.py
ckanext/chatbot/utils.py
ckanext/chatbot/views.py
ckanext/chatbot/assets/script.js
ckanext/chatbot/assets/style.css
ckanext/chatbot/assets/webassets.yml
ckanext/chatbot/templates/header.html
ckanext/chatbot/templates/chatbot/talk.html
ckanext/chatbot/tests/__init__.py
ckanext/chatbot/tests/test_plugin.py
ckanext_chatbot-0.0.12.dist-info/LICENSE
ckanext_chatbot-0.0.12.dist-info/METADATA
ckanext_chatbot-0.0.12.dist-info/WHEEL
ckanext_chatbot-0.0.12.dist-info/entry_points.txt
ckanext_chatbot-0.0.12.dist-info/top_level.txt
ckanext_chatbot-0.0.12.dist-info/RECORD
